trnpy/__init__.py
trnpy/exceptions.py
trnpy/trnsys/__init__.py
trnpy/trnsys/lib.py
trnpy/trnsys/simulation.py
trnpy-0.2.1.dist-info/METADATA
trnpy-0.2.1.dist-info/WHEEL
trnpy-0.2.1.dist-info/licenses/LICENSE
trnpy-0.2.1.dist-info/RECORD
